<?xml version = '1.0' encoding = 'UTF-8'?>
<FKIndexAssociation class="oracle.dbtools.crest.model.design.relational.FKIndexAssociation" id="ACDF9357-08AF-72B1-4134-EEF27DB5E1A6" directorySegmentName="seg_1" name="FK_STG_AGR">
<createdBy>Scott</createdBy>
<createdTime>2012-09-27 11:51:23 UTC</createdTime>
<generatorID>81F5B2F6-93D4-AFBB-F700-A1A61D0445D8</generatorID>
<ownerDesignName>Population Statistics Reference</ownerDesignName>
<containerWithKeyObject>E044B429-8BDF-4BAB-D2D2-18F8A838995C</containerWithKeyObject>
<deleteRule>RESTRICT</deleteRule>
<localFKIndex>82B9BA4F-0D8F-F05C-8A88-CB51E3C3A58A</localFKIndex>
<keyObject>EDF364B0-D5F6-A006-D793-A0E9FC8A060B</keyObject>
<mandatory>false</mandatory>
<transferable>false</transferable>
</FKIndexAssociation>